{
    "news": [
        {
            "title": "Police Blotter: Mezuzah theft and hit-and-run",
            "date": "Wed, Nov 8",
            "link": "https://stanforddaily.com/2023/11/08/police-blotter-mezuzah-theft-and-hit-and-run/"
        },
        {
            "title": "Hit-and-run injures Arab Muslim student, incident under investigation as hate crime",
            "date": "Sat, Nov 4",
            "link": "https://stanforddaily.com/2023/11/04/hit-and-run-injures-arab-muslim-student-incident-under-investigation-as-hate-crime/"
        }
    ]
}